setup.py
ain/__init__.py
ain/ain.py
ain/constants.py
ain/instanceUtil.py
ain/workerMgr.py
ain/share/worker.env
ain/share/log/log.env
ainainainain.egg-info/PKG-INFO
ainainainain.egg-info/SOURCES.txt
ainainainain.egg-info/dependency_links.txt
ainainainain.egg-info/entry_points.txt
ainainainain.egg-info/requires.txt
ainainainain.egg-info/top_level.txt