Metadata-Version: 1.2
Name: ainainainain
Version: 3.0
Summary: CLI of ainainainain a Python script
Home-page: https://bitbucket.org/comcomai/ain-v1-worker
License: BSD
Platform: UNKNOWN
Classifier: License :: OSI Approved :: BSD License
Requires-Python: >=3
